MANIFEST.in
README.md
camera_utils.py
mesh_renderer.py
rasterize_triangles.py
setup.py
mesh_renderer.egg-info/PKG-INFO
mesh_renderer.egg-info/SOURCES.txt
mesh_renderer.egg-info/dependency_links.txt
mesh_renderer.egg-info/top_level.txt
mesh_renderer/kernels/rasterize_triangles_grad.cc
mesh_renderer/kernels/rasterize_triangles_impl.cc
mesh_renderer/kernels/rasterize_triangles_impl.h
mesh_renderer/kernels/rasterize_triangles_op.cc