Metadata-Version: 2.1
Name: mesh-renderer
Version: 1.4
Summary: UNKNOWN
Home-page: https://github.com/JonathanRaiman/tf_mesh_renderer
Author: Jonathan Raiman
Author-email: raiman@openai.com
License: UNKNOWN
Download-URL: https://github.com/JonathanRaiman/tf_mesh_renderer
Platform: any
